<SCHEMA NAME="2014.00.MSG.PROD.AUTO"
        ID_FIELD_NAMES="MESSAGE-TYPE.MESSAGE-SUBTYPE.PROD-TYPE">
	<!-- pp 259, 261-262 of GMSEC Interface Spec 2014-02.docx -->
	<FIELD  NAME="HEADER-VERSION"
	        MODE="REQUIRED"
	        FIELD_CLASS="HEADER"
                VALUE="2010"
                TYPE="F32"
                DESCRIPTION="Version Number for this message description."/>
	<FIELD  NAME="MESSAGE-TYPE"
	        MODE="REQUIRED"
	        FIELD_CLASS="HEADER"
	        VALUE="MSG"
	        TYPE="STRING"
	        DESCRIPTION="Message type identifier: REQ, RESP, or MSG"/>
	<FIELD  NAME="MESSAGE-SUBTYPE"
	        MODE="REQUIRED"
	        FIELD_CLASS="HEADER"
	        VALUE="PROD"
	        TYPE="STRING"
	        DESCRIPTION="Unique message identifier, fixed for GMSEC Standard Messages"/>
	<FIELD  NAME="CONTENT-VERSION"
	        MODE="REQUIRED"
	        FIELD_CLASS="HEADER"
	        VALUE="2013"
	        TYPE="F32"
	        DESCRIPTION="Version Number for this message content description"/>
	<FIELD  NAME="MSG-ID"
	        MODE="OPTIONAL"
	        FIELD_CLASS="HEADER"
	        VALUE=""
	        TYPE="STRING"
	        DESCRIPTION="Echo of the MSG-ID field from the Product Request message."/>
	<FIELD  NAME="FINAL-MESSAGE"
	        MODE="OPTIONAL"
	        FIELD_CLASS="STANDARD"
	        VALUE="FALSE"
	        TYPE="BOOLEAN"
	        DESCRIPTION="When true, indicates the last message in the stream."/>
	<FIELD  NAME="RESPONSE-STATUS"
	        MODE="REQUIRED"
	        FIELD_CLASS="STANDARD"
	        VALUE="1"
	        TYPE="I16"
	        DESCRIPTION="Identifies the status of the Product Message that was processed.  Note: Even though a Request is valid, a product may not be able to be successfully generated.  In this case the following Product Message would indicate a Failed Completion."/>
	<FIELD  NAME="TIME-COMPLETED"
	        MODE="OPTIONAL"
	        FIELD_CLASS="STANDARD"
	        VALUE=""
	        TYPE="STRING"
	        DESCRIPTION="Time application created the product"/>
	<FIELD  NAME="RETURN-VALUE"
	        MODE="OPTIONAL"
	        FIELD_CLASS="STANDARD"
	        VALUE="0"
	        TYPE="I32"
	        DESCRIPTION="Return value or status based on the RESPONSE-STATUS.  Used to provide function call status or error code in the case of failed completion"/>
	<FIELD  NAME="DELIVER-VIA-REFERENCE"
	        MODE="OPTIONAL"
	        FIELD_CLASS="STANDARD"
	        VALUE="FALSE"
	        TYPE="BOOLEAN"
	        DESCRIPTION="Indicates the product is referenced by a URI.  A product can be included in a message, referenced by a URI, or both."/>
	<FIELD  NAME="DELIVER-VIA-INCLUDE"
	        MODE="OPTIONAL"
	        FIELD_CLASS="STANDARD"
	        VALUE="FALSE"
	        TYPE="BOOLEAN"
	        DESCRIPTION="Indicates the product is included in this message.  A product can be included in a message, referenced by a URI, or both."/>
	<FIELD  NAME="PROD-MSGS-TO-SEND"
	        MODE="OPTIONAL"
	        FIELD_CLASS="STANDARD"
	        VALUE="0"
	        TYPE="I16"
	        DESCRIPTION="Indicates the number of PROD Msgs that will be published to satisfy the PROD REQ."/>
	<FIELD  NAME="PROD-SEQ-NUM"
	        MODE="OPTIONAL"
	        FIELD_CLASS="STANDARD"
	        VALUE="1"
	        TYPE="I16"
	        DESCRIPTION="Indicates which message this is in the sequence of PROD Msgs that constitutes a product."/>
	<FIELD  NAME="PROD-NAME"
	        MODE="OPTIONAL"
	        FIELD_CLASS="STANDARD"
	        VALUE=""
	        TYPE="STRING"
	        DESCRIPTION="Name of the product"/>
	<FIELD  NAME="PROD-DESCRIPTION"
	        MODE="OPTIONAL"
	        FIELD_CLASS="STANDARD"
	        VALUE=""
	        TYPE="STRING"
	        DESCRIPTION="Description of the product in text or xml"/>
	<FIELD  NAME="PROD-TYPE"
	        MODE="REQUIRED"
	        FIELD_CLASS="STANDARD"
	        VALUE="AUTO"
	        TYPE="STRING"
	        DESCRIPTION="Category of product.  Could be echo of the PROD-TYPE field from the Product Request message."/>
	<FIELD  NAME="PROD-SUBTYPE"
	        MODE="REQUIRED"
	        FIELD_CLASS="STANDARD"
	        VALUE="DM"
	        TYPE="STRING"
	        DESCRIPTION="Subcategory of the product.  Could be echo of the PROD-SUBTYPE field of the Product Request Message."/>
	<FIELD  NAME="NUM-OF-PROD-SUBTYPES"
	        MODE="OPTIONAL"
	        FIELD_CLASS="STANDARD"
	        VALUE="1"
	        TYPE="I16"
	        DESCRIPTION="Number of further delineations / categories beyond the product subtype.  Also, used as msg subject elements ME5, ME6, etc. in Product Message."/>
	<FIELD  NAME="PROD-SUBTYPE.1.NAME"
	        MODE="OPTIONAL"
	        FIELD_CLASS="STANDARD"
	        VALUE=""
	        TYPE="STRING"
	        DESCRIPTION="First subcategory of the product subtype.  (Subject elements ME5, ME6, etc.)"/>
	<FIELD  NAME="NUM-OF-FILES"
	        MODE="OPTIONAL"
	        FIELD_CLASS="STANDARD"
	        VALUE="0"
	        TYPE="I16"
	        DESCRIPTION="Indicates the number of files included in this response message."/>
	<FIELD  NAME="FILE.1.URI"
	        MODE="OPTIONAL"
	        FIELD_CLASS="STANDARD"
	        VALUE=""
	        TYPE="STRING"
	        DESCRIPTION="URI specifying the location where the file of the product is stored"/>
	<FIELD  NAME="FILE.1.NAME-PATTERN"
	        MODE="OPTIONAL"
	        FIELD_CLASS="STANDARD"
	        VALUE=""
	        TYPE="STRING"
	        DESCRIPTION="Describes the file name"/>
	<FIELD  NAME="FILE.1.DESCRIPTION"
	        MODE="OPTIONAL"
	        FIELD_CLASS="STANDARD"
	        VALUE=""
	        TYPE="STRING"
	        DESCRIPTION="Description of the file in text or xml"/>
	<FIELD  NAME="FILE.1.FORMAT"
	        MODE="OPTIONAL"
	        FIELD_CLASS="STANDARD"
	        VALUE=""
	        TYPE="STRING"
	        DESCRIPTION="Describes the file format."/>
	<FIELD  NAME="FILE.1.VERSION"
	        MODE="OPTIONAL"
	        FIELD_CLASS="STANDARD"
	        VALUE=""
	        TYPE="STRING"
	        DESCRIPTION="Identifies the version ID of the file"/>
	<FIELD  NAME="FILE.1.SIZE"
	        MODE="OPTIONAL"
	        FIELD_CLASS="STANDARD"
	        VALUE="0"
	        TYPE="I32"
	        DESCRIPTION="Size of the included file"/>
	<FIELD  NAME="FILE.1.DATA"
	        MODE="OPTIONAL"
	        FIELD_CLASS="STANDARD"
	        VALUE="0"
	        TYPE="BLOB"
	        DESCRIPTION="The file content"/>
</SCHEMA>
